mirouterpy/__init__.py
mirouterpy/utils.py
mirouterpy-0.1.1.dist-info/LICENSE.md
mirouterpy-0.1.1.dist-info/METADATA
mirouterpy-0.1.1.dist-info/WHEEL
mirouterpy-0.1.1.dist-info/top_level.txt
mirouterpy-0.1.1.dist-info/RECORD
